DrSploitberg/__init__.py
DrSploitberg/attack/DoS.py
DrSploitberg/attack/__init__.py
DrSploitberg/enumeration/PortScanner.py
DrSploitberg/enumeration/__init__.py
DrSploitberg-0.1a1.dist-info/LICENSE
DrSploitberg-0.1a1.dist-info/METADATA
DrSploitberg-0.1a1.dist-info/WHEEL
DrSploitberg-0.1a1.dist-info/top_level.txt
DrSploitberg-0.1a1.dist-info/RECORD
