Metadata-Version: 2.1
Name: DrSploitberg
Version: 0.1a1
Summary: Dr.Sploitberg is a library of tools to aide with ethical hacking.
Home-page: UNKNOWN
Author: TeamSploitberg
Author-email: TeamSploitberg@outlook.com
License: MIT
Project-URL: GitHub, https://github.com/TeamSploitberg/Dr.Sploitberg
Project-URL: Bug Tracker, https://github.com/TeamSploitberg/Dr.Sploitberg/issues
Project-URL: Wiki, https://drsploitberg.readthedocs.io/en/latest/
Platform: UNKNOWN
Classifier: Programming Language :: Python :: 3
Classifier: License :: OSI Approved :: MIT License
Classifier: Operating System :: OS Independent
Requires-Python: >=3.6
